helpers/__init__.py
helpers/base64_helper.py
helpers/binascii_helper.py
helpers/common_helper.py
helpers/configparser_helper.py
helpers/crypto_js_helper.py
helpers/csv_helper.py
helpers/datetime_helper.py
helpers/dingtalk_helper.py
helpers/dnspython_helper.py
helpers/docxtpl_helper.py
helpers/gmssl_helper.py
helpers/hashlib_helper.py
helpers/ipaddress_helper.py
helpers/json_helper.py
helpers/loguru_helper.py
helpers/md5_crack_helper.py
helpers/openpyxl_helper.py
helpers/paramiko_helper.py
helpers/pbe_for_js_helper.py
helpers/pbe_for_py_helper.py
helpers/pycryptodome_helper.py
helpers/pymysql_helper.py
helpers/pyttsx3_helper.py
helpers/pywin32_helper.py
helpers/pyzipper_helper.py
helpers/re_helper.py
helpers/ruamel_yaml_helper.py
helpers/sm_crypto_helper.py
helpers/sqlite_helper.py
helpers/time_helper.py
helpers/tmpdb_helper.py
helpers/tripledes_helper.py
helpers/tshark_helper.py
helpers/werkzeug_helper.py
helpers/xlrd_helper.py
helpers/xlsxwriter_helper.py
helpers/xlwings_helper.py
helpers/xlwt_helper.py
helpers/yaml_helper.py
helpers/zipfile_helper.py
helpers/zmail_helper.py
sh2d-2025.7.16.dist-info/METADATA
sh2d-2025.7.16.dist-info/WHEEL
sh2d-2025.7.16.dist-info/top_level.txt
sh2d-2025.7.16.dist-info/RECORD
