Metadata-Version: 2.4
Name: sh2d
Version: 2025.7.16
Home-page: https://github.com/
Author: sh2d
Author-email: xx@qq.com
Classifier: Programming Language :: Python :: 3
Classifier: License :: OSI Approved :: MIT License
Classifier: Operating System :: OS Independent
Requires-Dist: colorlog
Requires-Dist: ddddocr
Requires-Dist: docxtpl
Requires-Dist: dnspython
Requires-Dist: gmssl
Requires-Dist: loguru
Requires-Dist: openpyxl
Requires-Dist: paramiko
Requires-Dist: pycryptodome
Requires-Dist: pyexecjs2
Requires-Dist: pymysql
Requires-Dist: python-docx
Requires-Dist: python-whois
Requires-Dist: pyttsx3
Requires-Dist: pywin32
Requires-Dist: pyyaml
Requires-Dist: pyzipper
Requires-Dist: requests
Requires-Dist: ruamel.yaml
Requires-Dist: werkzeug
Requires-Dist: xlwings
Requires-Dist: xlrd==1.2.0
Requires-Dist: xlsxwriter
Requires-Dist: xlwt
Requires-Dist: zmail
Dynamic: author
Dynamic: author-email
Dynamic: classifier
Dynamic: description-content-type
Dynamic: home-page
Dynamic: requires-dist
